{"client":"Thunder Client","collectionName":"grade-attendance-management","dateExported":"2021-09-03T07:33:05.354Z","version":"1.1","folders":[{"containerId":"","sortNum":10000,"name":"student","_id":"6acb98cd-e535-44bc-a08d-eebf77c99e83","created":"2021-09-03T05:30:10.349Z"}],"requests":[{"containerId":"6acb98cd-e535-44bc-a08d-eebf77c99e83","sortNum":10000,"headers":[{"name":"Accept","value":"*/*"},{"name":"User-Agent","value":"Thunder Client (https://www.thunderclient.io)"}],"colId":"0f48631c-2a66-4862-9375-c6d0599dee2d","name":"[STUDENT] create","url":"{{HOST}}/api/student","method":"POST","modified":"2021-09-03T07:27:44.868Z","created":"2021-09-03T05:17:30.849Z","_id":"3c937c03-330a-4a0d-9460-efbde10c8645","params":[],"body":{"type":"json","raw":"{\n    \"firstname\":\"test\",\n    \"lastname\":\"test\",\n    \"studentCode\":\"123456789\"\n}","form":[]},"tests":[]},{"containerId":"6acb98cd-e535-44bc-a08d-eebf77c99e83","sortNum":15000,"headers":[{"name":"Accept","value":"*/*"},{"name":"User-Agent","value":"Thunder Client (https://www.thunderclient.io)"}],"colId":"0f48631c-2a66-4862-9375-c6d0599dee2d","name":"[STUDENT] createFromCSV","url":"{{HOST}}/api/student/file","method":"POST","modified":"2021-09-03T07:10:05.455Z","created":"2021-09-03T06:49:07.614Z","_id":"4b4d3e4d-24ed-46c1-9419-c2409e752f5b","params":[],"body":{"type":"json","raw":"[\n  {\n    \"studentCode\": \"1248166\",\n    \"firstname\": \"ANDERSON TOMAS\",\n    \"lastname\": \"ADRIAN VIDAL\"\n  },\n  {\n    \"studentCode\": \"1248167\",\n    \"firstname\": \"JHEANPIER MARUAN\",\n    \"lastname\": \"AGUILAR AVILA\"\n  },\n  {\n    \"studentCode\": \"1248168\",\n    \"firstname\": \"MARCO ANTONIO\",\n    \"lastname\": \"ALVAN GIRALDO\"\n  },\n  {\n    \"studentCode\": \"1248169\",\n    \"firstname\": \"JOSEPH HABACUC\",\n    \"lastname\": \"ALVAREZ HUAMAN\"\n  },\n  {\n    \"studentCode\": \"1248170\",\n    \"firstname\": \"CARLOS DEL PIERO\",\n    \"lastname\": \"BANCES VASQUEZ\"\n  },\n  {\n    \"studentCode\": \"1248171\",\n    \"firstname\": \"PAMELA NICOLE\",\n    \"lastname\": \"BRONCANO OLORTEGUI\"\n  },\n  {\n    \"studentCode\": \"1248172\",\n    \"firstname\": \"ARTHUR SMITH\",\n    \"lastname\": \"CALDERON GUEVARA\"\n  },\n  {\n    \"studentCode\": \"1248173\",\n    \"firstname\": \"MIRKO PAVEL\",\n    \"lastname\": \"CAPURRO BUSTAMANTE\"\n  },\n  {\n    \"studentCode\": \"874254\",\n    \"firstname\": \"OLGUI ALEXANDER\",\n    \"lastname\": \"CERNA REGALADO\"\n  },\n  {\n    \"studentCode\": \"1248200\",\n    \"firstname\": \"BRYAN MARTIN\",\n    \"lastname\": \"DE LA VIA JULON\"\n  },\n  {\n    \"studentCode\": \"1248201\",\n    \"firstname\": \"ANTHONY BRAYAN\",\n    \"lastname\": \"ECHEVARRIA CONDOR\"\n  },\n  {\n    \"studentCode\": \"1248205\",\n    \"firstname\": \"MARIA ISABEL\",\n    \"lastname\": \"FERNANDEZ PAREDES\"\n  },\n  {\n    \"studentCode\": \"1248206\",\n    \"firstname\": \"ANGEL ORLANDO\",\n    \"lastname\": \"GONZALES ACEVEDO\"\n  },\n  {\n    \"studentCode\": \"1248210\",\n    \"firstname\": \"LUIS RONALDO\",\n    \"lastname\": \"LEON SALDAÑA\"\n  },\n  {\n    \"studentCode\": \"1248214\",\n    \"firstname\": \"ROBERTO JUNIOR\",\n    \"lastname\": \"MATTOS CENTURION\"\n  },\n  {\n    \"studentCode\": \"1248215\",\n    \"firstname\": \"IRENE BRIGGITH\",\n    \"lastname\": \"MAZA LAZARO\"\n  },\n  {\n    \"studentCode\": \"1248216\",\n    \"firstname\": \"FLAVIO RODRIGO\",\n    \"lastname\": \"MENDOZA MENESES\"\n  },\n  {\n    \"studentCode\": \"1248220\",\n    \"firstname\": \"YARITZA MASIEL\",\n    \"lastname\": \"MIRANDA SAAVEDRA\"\n  },\n  {\n    \"studentCode\": \"1248223\",\n    \"firstname\": \"MARCIAL SANTOS\",\n    \"lastname\": \"MONTES GIRALDO\"\n  },\n  {\n    \"studentCode\": \"1248225\",\n    \"firstname\": \"JHARIXA IRAIDA\",\n    \"lastname\": \"SOTO QUEZADA\"\n  },\n  {\n    \"studentCode\": \"1248229\",\n    \"firstname\": \"MARK ANDERSON\",\n    \"lastname\": \"VEGA PUMA\"\n  },\n  {\n    \"studentCode\": \"1248236\",\n    \"firstname\": \"DANIEL ESTEBAN\",\n    \"lastname\": \"VILLALTA BALCAZAR\"\n  }\n]","form":[]},"tests":[]},{"containerId":"6acb98cd-e535-44bc-a08d-eebf77c99e83","sortNum":20000,"headers":[{"name":"Accept","value":"*/*"},{"name":"User-Agent","value":"Thunder Client (https://www.thunderclient.io)"}],"colId":"0f48631c-2a66-4862-9375-c6d0599dee2d","name":"[STUDENT] getAll","url":"{{HOST}}/api/student","method":"GET","modified":"2021-09-03T07:28:12.162Z","created":"2021-09-03T06:16:57.755Z","_id":"483e6bd4-476b-4bac-bc6b-e67db1e8215d","params":[],"tests":[]},{"containerId":"","sortNum":20000,"headers":[{"name":"Accept","value":"*/*"},{"name":"User-Agent","value":"Thunder Client (https://www.thunderclient.io)"}],"colId":"0f48631c-2a66-4862-9375-c6d0599dee2d","name":"test Copy","url":"{{HOST}}/api/student","method":"POST","modified":"2021-09-03T05:29:25.778Z","created":"2021-09-03T05:29:25.778Z","_id":"7ef6d846-adda-47ec-b181-6df2956ea9f7","params":[],"tests":[]},{"containerId":"6acb98cd-e535-44bc-a08d-eebf77c99e83","sortNum":30000,"headers":[{"name":"Accept","value":"*/*"},{"name":"User-Agent","value":"Thunder Client (https://www.thunderclient.io)"}],"colId":"0f48631c-2a66-4862-9375-c6d0599dee2d","name":"[STUDENT] update","url":"{{HOST}}/api/student/1","method":"PUT","modified":"2021-09-03T06:29:49.766Z","created":"2021-09-03T06:27:58.221Z","_id":"504b2485-2d14-4f43-bf6c-13d1e9224915","params":[],"body":{"type":"json","raw":"{\n    \"firstname\":\"test-update\",\n    \"lastname\":\"test-update\",\n    \"studentCode\":\"21111111\"\n}","form":[]},"tests":[]},{"containerId":"6acb98cd-e535-44bc-a08d-eebf77c99e83","sortNum":40000,"headers":[{"name":"Accept","value":"*/*"},{"name":"User-Agent","value":"Thunder Client (https://www.thunderclient.io)"}],"colId":"0f48631c-2a66-4862-9375-c6d0599dee2d","name":"[STUDENT] getById","url":"{{HOST}}/api/student/2","method":"GET","modified":"2021-09-03T06:45:13.310Z","created":"2021-09-03T06:33:51.246Z","_id":"0fbc7ce8-77b2-4c3f-a227-7dfe3e78db1d","params":[],"tests":[]},{"containerId":"6acb98cd-e535-44bc-a08d-eebf77c99e83","sortNum":50000,"headers":[{"name":"Accept","value":"*/*"},{"name":"User-Agent","value":"Thunder Client (https://www.thunderclient.io)"}],"colId":"0f48631c-2a66-4862-9375-c6d0599dee2d","name":"[STUDENT] delete","url":"{{HOST}}/api/student/2","method":"DELETE","modified":"2021-09-03T07:29:13.851Z","created":"2021-09-03T06:33:53.316Z","_id":"8a63046f-0332-40bc-8468-2cb6e07fdd50","params":[],"tests":[]}]}
